CONTRIBUTING.md
MANIFEST.in
README.md
setup.cfg
setup.py
src/acqdiv/__init__.py
src/acqdiv/__main__.py
src/acqdiv/config.ini
src/acqdiv/loader.py
src/acqdiv.egg-info/PKG-INFO
src/acqdiv.egg-info/SOURCES.txt
src/acqdiv.egg-info/dependency_links.txt
src/acqdiv.egg-info/entry_points.txt
src/acqdiv.egg-info/requires.txt
src/acqdiv.egg-info/top_level.txt
src/acqdiv/database/README.md
src/acqdiv/database/__init__.py
src/acqdiv/database/model.py
src/acqdiv/database/processor.py
src/acqdiv/database/sqlite_to_r.R
src/acqdiv/database/views.sql
src/acqdiv/model/__init__.py
src/acqdiv/model/corpus.py
src/acqdiv/model/morpheme.py
src/acqdiv/model/session.py
src/acqdiv/model/speaker.py
src/acqdiv/model/uniquespeaker.py
src/acqdiv/model/utterance.py
src/acqdiv/model/word.py
src/acqdiv/parsers/__init__.py
src/acqdiv/parsers/corpus_parser.py
src/acqdiv/parsers/corpus_parser_mapper.py
src/acqdiv/parsers/session_parser.py
src/acqdiv/parsers/chat/README.md
src/acqdiv/parsers/chat/__init__.py
src/acqdiv/parsers/chat/parser.py
src/acqdiv/parsers/chat/cleaners/__init__.py
src/acqdiv/parsers/chat/cleaners/cleaner.py
src/acqdiv/parsers/chat/cleaners/utterance_cleaner.py
src/acqdiv/parsers/chat/cleaners/word_cleaner.py
src/acqdiv/parsers/chat/model/__init__.py
src/acqdiv/parsers/chat/model/chat.py
src/acqdiv/parsers/chat/model/participant.py
src/acqdiv/parsers/chat/model/record.py
src/acqdiv/parsers/chat/readers/__init__.py
src/acqdiv/parsers/chat/readers/actual_target_utterance.py
src/acqdiv/parsers/chat/readers/fileparser.py
src/acqdiv/parsers/chat/readers/reader.py
src/acqdiv/parsers/chat/readers/sentence_type.py
src/acqdiv/parsers/corpora/__init__.py
src/acqdiv/parsers/corpora/main/__init__.py
src/acqdiv/parsers/corpora/main/chintang/__init__.py
src/acqdiv/parsers/corpora/main/chintang/cleaner.py
src/acqdiv/parsers/corpora/main/chintang/corpus_parser.py
src/acqdiv/parsers/corpora/main/chintang/gloss_mapper.py
src/acqdiv/parsers/corpora/main/chintang/imdi_parser.py
src/acqdiv/parsers/corpora/main/chintang/pos_mapper.py
src/acqdiv/parsers/corpora/main/chintang/reader.py
src/acqdiv/parsers/corpora/main/chintang/session_parser.py
src/acqdiv/parsers/corpora/main/chintang/tc_cleaner.py
