Metadata-Version: 2.1
Name: acqdiv
Version: 1.1.0
Summary: Pipeline for the ACQDIV database
Home-page: https://github.com/acqdiv/acqdiv
Author: ACQDIV developer team
License: UNKNOWN
Project-URL: Bug Reports, https://github.com/acqdiv/acqdiv/issues
Project-URL: Source, https://github.com/acqdiv/acqdiv
Keywords: data linguistics
Platform: UNKNOWN
Classifier: Development Status :: 5 - Production/Stable
Classifier: Intended Audience :: Developers
Classifier: Topic :: Text Processing :: Linguistic
Classifier: Programming Language :: Python
Classifier: Programming Language :: Python :: 3
Classifier: Programming Language :: Python :: 3.6
Classifier: Programming Language :: Python :: 3.7
Requires-Python: >=3.6
Provides-Extra: dev
Provides-Extra: test
